DioHash.py
DioHash-2.1.1.dist-info/DESCRIPTION.rst
DioHash-2.1.1.dist-info/METADATA
DioHash-2.1.1.dist-info/RECORD
DioHash-2.1.1.dist-info/WHEEL
DioHash-2.1.1.dist-info/metadata.json
DioHash-2.1.1.dist-info/top_level.txt
