Metadata-Version: 2.0
Name: DioHash
Version: 2.1.1
Summary: UNKNOWN
Home-page: https://github.com/sukreshmanda/DioHash
Author: Manda Sukresh
Author-email: mandasukresh@gmail.com
License: UNKNOWN
Platform: UNKNOWN
Classifier: Programming Language :: Python :: 3
Classifier: Programming Language :: Python :: 3.6
Classifier: Programming Language :: Python :: 3.7
Classifier: License :: OSI Approved :: GNU General Public License v3 or later (GPLv3+)
Classifier: Operating System :: OS Independent
